LICENSE
MANIFEST.in
README.md
setup.py
django_phantom_pdf.egg-info/PKG-INFO
django_phantom_pdf.egg-info/SOURCES.txt
django_phantom_pdf.egg-info/dependency_links.txt
django_phantom_pdf.egg-info/top_level.txt
docs/example_project/manage.py
docs/example_project/phantom_pdf_poc/__init__.py
docs/example_project/phantom_pdf_poc/settings.py
docs/example_project/phantom_pdf_poc/urls.py
docs/example_project/phantom_pdf_poc/wsgi.py
docs/example_project/poc/__init__.py
docs/example_project/poc/admin.py
docs/example_project/poc/models.py
docs/example_project/poc/tests.py
docs/example_project/poc/views.py
phantom_pdf/__init__.py
phantom_pdf/generator.py
phantom_pdf/models.py
phantom_pdf_bin/__init__.py
phantom_pdf_bin/generate_pdf.js