Metadata-Version: 1.1
Name: django-phantom-pdf
Version: 0.3
Summary: A simple django app for creating pdf files.
Home-page: https://github.com/BananaDesk/django-phantom-pdf
Author: Juan Carizza, Tim Zenderman, Emiliano Dalla Verde Marcozzi
Author-email: juan.carizza@gmail.com, tzenderman@gmail.com, edvm@fedoraproject.org
License: BSD License
Download-URL: https://github.com/BananaDesk/django-phantom-pdf/archive/v0.3.tar.gz
Platform: UNKNOWN
Classifier: Environment :: Web Environment
Classifier: Framework :: Django
Classifier: Intended Audience :: Developers
Classifier: License :: OSI Approved :: BSD License
Classifier: Operating System :: OS Independent
Classifier: Programming Language :: Python
Classifier: Programming Language :: Python :: 2.7
Classifier: Topic :: Internet :: WWW/HTTP
Classifier: Topic :: Utilities
